alibabacloud_ehpcinstant20230701/__init__.py
alibabacloud_ehpcinstant20230701/client.py
alibabacloud_ehpcinstant20230701/models/__init__.py
alibabacloud_ehpcinstant20230701/models/_add_image_request.py
alibabacloud_ehpcinstant20230701/models/_add_image_response.py
alibabacloud_ehpcinstant20230701/models/_add_image_response_body.py
alibabacloud_ehpcinstant20230701/models/_add_image_shrink_request.py
alibabacloud_ehpcinstant20230701/models/_create_action_plan_request.py
alibabacloud_ehpcinstant20230701/models/_create_action_plan_response.py
alibabacloud_ehpcinstant20230701/models/_create_action_plan_response_body.py
alibabacloud_ehpcinstant20230701/models/_create_action_plan_shrink_request.py
alibabacloud_ehpcinstant20230701/models/_create_job_request.py
alibabacloud_ehpcinstant20230701/models/_create_job_response.py
alibabacloud_ehpcinstant20230701/models/_create_job_response_body.py
alibabacloud_ehpcinstant20230701/models/_create_job_shrink_request.py
alibabacloud_ehpcinstant20230701/models/_create_pool_request.py
alibabacloud_ehpcinstant20230701/models/_create_pool_response.py
alibabacloud_ehpcinstant20230701/models/_create_pool_response_body.py
alibabacloud_ehpcinstant20230701/models/_create_pool_shrink_request.py
alibabacloud_ehpcinstant20230701/models/_delete_action_plan_request.py
alibabacloud_ehpcinstant20230701/models/_delete_action_plan_response.py
alibabacloud_ehpcinstant20230701/models/_delete_action_plan_response_body.py
alibabacloud_ehpcinstant20230701/models/_delete_job_records_request.py
alibabacloud_ehpcinstant20230701/models/_delete_job_records_response.py
alibabacloud_ehpcinstant20230701/models/_delete_job_records_response_body.py
alibabacloud_ehpcinstant20230701/models/_delete_job_records_shrink_request.py
alibabacloud_ehpcinstant20230701/models/_delete_jobs_request.py
alibabacloud_ehpcinstant20230701/models/_delete_jobs_response.py
alibabacloud_ehpcinstant20230701/models/_delete_jobs_response_body.py
alibabacloud_ehpcinstant20230701-3.5.2.dist-info/LICENSE
alibabacloud_ehpcinstant20230701-3.5.2.dist-info/METADATA
alibabacloud_ehpcinstant20230701-3.5.2.dist-info/WHEEL
alibabacloud_ehpcinstant20230701-3.5.2.dist-info/top_level.txt
alibabacloud_ehpcinstant20230701-3.5.2.dist-info/RECORD
